legalnlp
