Metadata-Version: 2.1
Name: legalnlp
Version: 1.0.3
Summary: Pre-trained language models forthe  Brazilian  legal  language.
Home-page: https://github.com/felipemaiapolo/legalnlp
Author: Felipe Maia Polo
Author-email: felipemaiapolo@gmail.com
License: UNKNOWN
Platform: UNKNOWN
Classifier: Programming Language :: Python :: 3
Classifier: License :: OSI Approved :: MIT License
Classifier: Operating System :: OS Independent
